klaude_code/.DS_Store
klaude_code/__init__.py
klaude_code/app/__init__.py
klaude_code/app/runtime.py
klaude_code/auth/AGENTS.md
klaude_code/auth/__init__.py
klaude_code/auth/antigravity/__init__.py
klaude_code/auth/antigravity/exceptions.py
klaude_code/auth/antigravity/oauth.py
klaude_code/auth/antigravity/pkce.py
klaude_code/auth/antigravity/token_manager.py
klaude_code/auth/base.py
klaude_code/auth/claude/__init__.py
klaude_code/auth/claude/exceptions.py
klaude_code/auth/claude/oauth.py
klaude_code/auth/claude/token_manager.py
klaude_code/auth/codex/__init__.py
klaude_code/auth/codex/exceptions.py
klaude_code/auth/codex/jwt_utils.py
klaude_code/auth/codex/oauth.py
klaude_code/auth/codex/token_manager.py
klaude_code/auth/env.py
klaude_code/cli/__init__.py
klaude_code/cli/auth_cmd.py
klaude_code/cli/config_cmd.py
klaude_code/cli/cost_cmd.py
klaude_code/cli/debug.py
klaude_code/cli/list_model.py
klaude_code/cli/main.py
klaude_code/cli/self_update.py
klaude_code/config/__init__.py
klaude_code/config/assets/__init__.py
klaude_code/config/assets/builtin_config.yaml
klaude_code/config/builtin_config.py
klaude_code/config/config.py
klaude_code/config/model_matcher.py
klaude_code/config/sub_agent_model_helper.py
klaude_code/config/thinking.py
klaude_code/const.py
klaude_code/core/__init__.py
klaude_code/core/agent.py
klaude_code/core/agent_profile.py
klaude_code/core/bash_mode.py
klaude_code/core/compaction/AGENTS.md
klaude_code/core/compaction/__init__.py
klaude_code/core/compaction/compaction.py
klaude_code/core/compaction/overflow.py
klaude_code/core/compaction/prompts.py
klaude_code/core/executor.py
klaude_code/core/loaded_skills.py
klaude_code/core/manager/__init__.py
klaude_code/core/manager/llm_clients.py
klaude_code/core/manager/llm_clients_builder.py
klaude_code/core/manager/sub_agent_manager.py
klaude_code/core/memory.py
klaude_code/core/prompts/prompt-antigravity.md
klaude_code/core/prompts/prompt-claude-code.md
klaude_code-2.10.1.dist-info/WHEEL
klaude_code-2.10.1.dist-info/entry_points.txt
klaude_code-2.10.1.dist-info/METADATA
klaude_code-2.10.1.dist-info/RECORD
