Metadata-Version: 2.3
Name: klaude-code
Version: 2.10.1
Summary: Minimal code agent CLI
Requires-Dist: anthropic>=0.66.0
Requires-Dist: chardet>=5.2.0
Requires-Dist: ddgs>=9.9.3
Requires-Dist: diff-match-patch>=20241021
Requires-Dist: filelock>=3.20.3
Requires-Dist: google-genai>=1.56.0
Requires-Dist: markdown-it-py>=4.0.0
Requires-Dist: openai>=1.102.0
Requires-Dist: prompt-toolkit>=3.0.52
Requires-Dist: pydantic>=2.11.7
Requires-Dist: pyyaml>=6.0.2
Requires-Dist: rich>=14.1.0
Requires-Dist: trafilatura>=2.0.0
Requires-Dist: typer>=0.17.3
Requires-Python: >=3.13
